height2obj.py
height2obj-0.9.0.dist-info/METADATA
height2obj-0.9.0.dist-info/RECORD
height2obj-0.9.0.dist-info/WHEEL
height2obj-0.9.0.dist-info/entry_points.txt
height2obj-0.9.0.dist-info/top_level.txt
