Metadata-Version: 2.1
Name: height2obj
Version: 0.9.0
Summary: Converts heightmap to 3d mesh.
Home-page: https://bitbucket.org/sgeorg_htw/height2obj
Author: Sebastian Georg
Author-email: sebastian.georg@htwsaar.de
License: Apache License 2.0
Platform: UNKNOWN
Classifier: Development Status :: 3 - Alpha
Classifier: Environment :: Console
Classifier: License :: OSI Approved :: Apache Software License
Classifier: Operating System :: OS Independent
Classifier: Programming Language :: Python :: 3
Classifier: Programming Language :: Python :: 3.4
Classifier: Programming Language :: Python :: 3.5
Classifier: Programming Language :: Python :: 3.6
Classifier: Topic :: Multimedia :: Graphics :: 3D Modeling
Requires-Python: >=3
Requires-Dist: pillow
